{"status":true,"updated_at_utc":"2026-07-22 16:26:09","server_time":1784737569,"odds":{"1550600":{"home_team_id":1301,"away_team_id":92,"updated":18,"status":"First Half","match_winner":{"home":"2.3","draw":"1.833","away":"7"},"next_goal":{"home":null,"none":null,"away":null}},"1560777":{"home_team_id":47,"away_team_id":1348,"updated":26,"status":"First Half","match_winner":{"home":"1.1","draw":"7","away":"21"},"next_goal":null},"1560783":{"home_team_id":106,"away_team_id":2900,"updated":23,"status":"First Half","match_winner":{"home":"3.1","draw":"2.875","away":"2.2"},"next_goal":{"home":null,"none":null,"away":null}},"1560785":{"home_team_id":82,"away_team_id":9932,"updated":26,"status":"First Half","match_winner":{"home":"2.75","draw":"1.666","away":"6.5"},"next_goal":null},"1591895":{"home_team_id":492,"away_team_id":876,"updated":23,"status":"First Half","match_winner":{"home":"3.5","draw":"2.625","away":"2.2"},"next_goal":null},"1598506":{"home_team_id":5902,"away_team_id":5050,"updated":26,"status":"First Half","match_winner":{"home":"15","draw":"3.75","away":"1.25"},"next_goal":{"home":null,"none":null,"away":null}},"1516067":{"home_team_id":3695,"away_team_id":4209,"updated":66,"status":"Second Half","match_winner":null,"next_goal":null},"1516068":{"home_team_id":4213,"away_team_id":4215,"updated":65,"status":"Second Half","match_winner":null,"next_goal":null},"1560780":{"home_team_id":488,"away_team_id":870,"updated":70,"status":"Second Half","match_winner":null,"next_goal":null},"1560782":{"home_team_id":503,"away_team_id":17824,"updated":45,"status":"Halftime","match_winner":{"home":"6.5","draw":"1.111","away":"21"},"next_goal":{"home":null,"none":null,"away":null}},"1562955":{"home_team_id":162,"away_team_id":310,"updated":45,"status":"Halftime","match_winner":{"home":"1.045","draw":"11","away":"151"},"next_goal":{"home":null,"none":null,"away":null}},"1567703":{"home_team_id":83,"away_team_id":9915,"updated":45,"status":"Halftime","match_winner":{"home":"6.5","draw":"1.111","away":"21"},"next_goal":{"home":null,"none":null,"away":null}},"1584925":{"home_team_id":504,"away_team_id":1707,"updated":45,"status":"Halftime","match_winner":null,"next_goal":null},"1591894":{"home_team_id":867,"away_team_id":2606,"updated":45,"status":"Halftime","match_winner":null,"next_goal":{"home":null,"none":null,"away":null}}}}