{"status":true,"updated_at_utc":"2026-07-23 00:28:05","server_time":1784766485,"odds":{"1490331":{"home_team_id":9568,"away_team_id":1607,"updated":47,"status":"First Half","match_winner":{"home":"4","draw":"1.615","away":"4"},"next_goal":null},"1490332":{"home_team_id":2242,"away_team_id":1603,"updated":47,"status":"First Half","match_winner":{"home":"1.071","draw":"7.5","away":"126"},"next_goal":null},"1490333":{"home_team_id":1613,"away_team_id":1604,"updated":47,"status":"First Half","match_winner":{"home":"151","draw":"8.5","away":"1.055"},"next_goal":{"home":null,"none":null,"away":null}},"1490334":{"home_team_id":1599,"away_team_id":1602,"updated":47,"status":"First Half","match_winner":{"home":"7","draw":"1.142","away":"12"},"next_goal":null},"1492294":{"home_team_id":147,"away_team_id":121,"updated":93,"status":"Second Half","match_winner":null,"next_goal":null},"1490335":{"home_team_id":1609,"away_team_id":1601,"updated":45,"status":"Halftime","match_winner":{"home":"10","draw":"1.083","away":"15"},"next_goal":{"home":null,"none":null,"away":null}}}}