{"status":true,"updated_at_utc":"2026-07-20 17:36:06","server_time":1784568966,"odds":{"1494214":{"home_team_id":374,"away_team_id":375,"updated":35,"status":"First Half","match_winner":{"home":"1.125","draw":"6","away":"51"},"next_goal":null},"1494216":{"home_team_id":2166,"away_team_id":364,"updated":34,"status":"First Half","match_winner":{"home":"7","draw":"1.571","away":"3.4"},"next_goal":{"home":null,"none":null,"away":null}},"1497627":{"home_team_id":2173,"away_team_id":373,"updated":35,"status":"First Half","match_winner":{"home":"5.5","draw":"1.363","away":"6.5"},"next_goal":{"home":null,"none":null,"away":null}},"1495738":{"home_team_id":587,"away_team_id":1166,"updated":75,"status":"Second Half","match_winner":null,"next_goal":{"home":null,"none":null,"away":null}},"1515888":{"home_team_id":4143,"away_team_id":4138,"updated":79,"status":"Second Half","match_winner":null,"next_goal":null},"1551052":{"home_team_id":854,"away_team_id":853,"updated":60,"status":"Second Half","match_winner":{"home":"9.5","draw":"1.615","away":"2.6"},"next_goal":{"home":null,"none":null,"away":null}},"1567689":{"home_team_id":21390,"away_team_id":1025,"updated":81,"status":"Second Half","match_winner":null,"next_goal":null}}}