{"status":true,"updated_at_utc":"2026-07-04 18:36:04","server_time":1783190164,"odds":{"1498613":{"home_team_id":482,"away_team_id":465,"updated":3,"status":"First Half","match_winner":{"home":"6","draw":"1.222","away":"8.5"},"next_goal":{"home":null,"none":null,"away":null}},"1499497":{"home_team_id":8008,"away_team_id":459,"updated":33,"status":"First Half","match_winner":{"home":"6.5","draw":"1.333","away":"5"},"next_goal":null},"1499502":{"home_team_id":2429,"away_team_id":8385,"updated":29,"status":"First Half","match_winner":{"home":"1.111","draw":"6.5","away":"26"},"next_goal":null},"1567824":{"home_team_id":5529,"away_team_id":31,"updated":71,"status":"Second Half","match_winner":{"home":"101","draw":"6.5","away":"1.1"},"next_goal":{"home":null,"none":null,"away":null}}}}