{"status":true,"updated_at_utc":"2026-07-17 12:38:05","server_time":1784291885,"odds":{"1523205":{"home_team_id":21265,"away_team_id":836,"updated":37,"status":"First Half","match_winner":{"home":"41","draw":"4.75","away":"1.181"},"next_goal":{"home":null,"none":null,"away":null}},"1554977":{"home_team_id":199,"away_team_id":427,"updated":32,"status":"First Half","match_winner":{"home":"6.5","draw":"1.571","away":"3.1"},"next_goal":null},"1523203":{"home_team_id":830,"away_team_id":5684,"updated":45,"status":"Halftime","match_winner":{"home":"1.025","draw":"15","away":"401"},"next_goal":{"home":null,"none":null,"away":null}},"1547975":{"home_team_id":209,"away_team_id":736,"updated":45,"status":"Halftime","match_winner":{"home":"8","draw":"1.1","away":"17"},"next_goal":{"home":null,"none":null,"away":null}}}}