{"status":true,"updated_at_utc":"2026-07-16 20:18:05","server_time":1784233085,"odds":{"1554451":{"home_team_id":4165,"away_team_id":556,"updated":16,"status":"First Half","match_winner":{"home":"501","draw":"23","away":"1.004"},"next_goal":{"home":null,"none":null,"away":null}},"1554415":{"home_team_id":3740,"away_team_id":3345,"updated":74,"status":"Second Half","match_winner":{"home":"1.025","draw":"15","away":"251"},"next_goal":{"home":null,"none":null,"away":null}},"1554438":{"home_team_id":5308,"away_team_id":3499,"updated":59,"status":"Second Half","match_winner":{"home":"3.1","draw":"1.615","away":"5.5"},"next_goal":{"home":null,"none":null,"away":null}}}}