{"status":true,"updated_at_utc":"2026-07-19 13:14:05","server_time":1784466845,"odds":{"1497626":{"home_team_id":16601,"away_team_id":365,"updated":13,"status":"First Half","match_winner":{"home":"1.285","draw":"4.333","away":"17"},"next_goal":null},"1497632":{"home_team_id":2163,"away_team_id":2165,"updated":13,"status":"First Half","match_winner":{"home":"3.4","draw":"1.909","away":"3.75"},"next_goal":{"home":null,"none":null,"away":null}},"1546700":{"home_team_id":190,"away_team_id":174,"updated":54,"status":"Second Half","match_winner":null,"next_goal":null}}}