{"status":true,"updated_at_utc":"2026-07-22 19:00:18","server_time":1784746818,"odds":{"1548891":{"home_team_id":1838,"away_team_id":39,"updated":25,"status":"First Half","match_winner":{"home":"9.5","draw":"1.952","away":"1.952"},"next_goal":{"home":null,"none":null,"away":null}},"1548900":{"home_team_id":1341,"away_team_id":1337,"updated":30,"status":"First Half","match_winner":{"home":"29","draw":"10","away":"1.062"},"next_goal":null},"1556521":{"home_team_id":1120,"away_team_id":1426,"updated":30,"status":"First Half","match_winner":{"home":"4.333","draw":"1.444","away":"5.5"},"next_goal":{"home":null,"none":null,"away":null}},"1560792":{"home_team_id":748,"away_team_id":54,"updated":29,"status":"First Half","match_winner":{"home":"29","draw":"8","away":"1.083"},"next_goal":null},"1567707":{"home_team_id":719,"away_team_id":546,"updated":27,"status":"First Half","match_winner":{"home":"5.5","draw":"1.444","away":"4.5"},"next_goal":{"home":null,"none":null,"away":null}},"1560791":{"home_team_id":9413,"away_team_id":531,"updated":70,"status":"Second Half","match_winner":null,"next_goal":null},"1586122":{"home_team_id":18257,"away_team_id":15584,"updated":90,"status":"Second Half","match_winner":null,"next_goal":null},"1593477":{"home_team_id":564,"away_team_id":1164,"updated":57,"status":"Second Half","match_winner":{"home":"8.5","draw":"1.071","away":"21"},"next_goal":null},"1558474":{"home_team_id":24208,"away_team_id":27874,"updated":45,"status":"Halftime","match_winner":null,"next_goal":null},"1562958":{"home_team_id":532,"away_team_id":9692,"updated":45,"status":"Halftime","match_winner":null,"next_goal":null},"1583409":{"home_team_id":9403,"away_team_id":547,"updated":45,"status":"Halftime","match_winner":null,"next_goal":null},"1589430":{"home_team_id":574,"away_team_id":10124,"updated":45,"status":"Halftime","match_winner":null,"next_goal":null}}}