{"status":true,"updated_at_utc":"2026-07-08 17:08:03","server_time":1783530483,"odds":{"1546633":{"home_team_id":203,"away_team_id":422,"updated":8,"status":"First Half","match_winner":{"home":"2.05","draw":"2.4","away":"5"},"next_goal":{"home":null,"none":null,"away":null}},"1554369":{"home_team_id":7808,"away_team_id":632,"updated":7,"status":"First Half","match_winner":{"home":"23","draw":"6","away":"1.125"},"next_goal":{"home":null,"none":null,"away":null}},"1554370":{"home_team_id":2271,"away_team_id":3327,"updated":8,"status":"First Half","match_winner":{"home":"1.062","draw":"8.5","away":"126"},"next_goal":{"home":null,"none":null,"away":null}},"1554805":{"home_team_id":9354,"away_team_id":159,"updated":34,"status":"First Half","match_winner":{"home":"67","draw":"51","away":"1.002"},"next_goal":null},"1554807":{"home_team_id":206,"away_team_id":202,"updated":6,"status":"First Half","match_winner":{"home":"4.333","draw":"2.25","away":"2.375"},"next_goal":{"home":null,"none":null,"away":null}},"1554363":{"home_team_id":687,"away_team_id":3502,"updated":48,"status":"Second Half","match_winner":{"home":"81","draw":"7","away":"1.083"},"next_goal":null}}}