{"status":true,"updated_at_utc":"2026-07-17 01:36:04","server_time":1784252164,"odds":{"1490325":{"home_team_id":1614,"away_team_id":1601,"updated":92,"status":"Second Half","match_winner":null,"next_goal":{"home":null,"none":null,"away":null}},"1490327":{"home_team_id":20787,"away_team_id":1611,"updated":45,"status":"Halftime","match_winner":{"home":"1.03","draw":"13","away":"301"},"next_goal":null},"1540103":{"home_team_id":474,"away_team_id":451,"updated":45,"status":"Halftime","match_winner":null,"next_goal":{"home":null,"none":null,"away":null}}}}