{"status":true,"updated_at_utc":"2026-07-18 15:24:18","server_time":1784388258,"odds":{"1497630":{"home_team_id":2174,"away_team_id":2175,"updated":23,"status":"First Half","match_winner":{"home":"1.25","draw":"4.5","away":"17"},"next_goal":{"home":null,"none":null,"away":null}},"1528029":{"home_team_id":4564,"away_team_id":664,"updated":23,"status":"First Half","match_winner":null,"next_goal":null},"1528031":{"home_team_id":4562,"away_team_id":4552,"updated":24,"status":"First Half","match_winner":{"home":"3.4","draw":"1.615","away":"5"},"next_goal":{"home":null,"none":null,"away":null}},"1542337":{"home_team_id":33,"away_team_id":1837,"updated":22,"status":"First Half","match_winner":{"home":"2.875","draw":"1.833","away":"4.75"},"next_goal":{"home":null,"none":null,"away":null}},"1546699":{"home_team_id":1658,"away_team_id":165,"updated":0,"status":"Not Started","match_winner":{"home":"8","draw":"3.6","away":"1.4"},"next_goal":{"home":null,"none":null,"away":null}},"1560742":{"home_team_id":498,"away_team_id":6648,"updated":22,"status":"First Half","match_winner":{"home":"1.727","draw":"2.1","away":"17"},"next_goal":{"home":null,"none":null,"away":null}},"1560743":{"home_team_id":87,"away_team_id":431,"updated":19,"status":"First Half","match_winner":{"home":"3.75","draw":"1.8","away":"3.5"},"next_goal":{"home":null,"none":null,"away":null}},"1560757":{"home_team_id":15847,"away_team_id":4715,"updated":16,"status":"First Half","match_winner":{"home":"1.363","draw":"3.6","away":"9"},"next_goal":null},"1567682":{"home_team_id":9362,"away_team_id":169,"updated":21,"status":"First Half","match_winner":null,"next_goal":null},"1583386":{"home_team_id":76,"away_team_id":191,"updated":38,"status":"First Half","match_winner":{"home":"5.5","draw":"1.333","away":"5.5"},"next_goal":null},"1494702":{"home_team_id":320,"away_team_id":333,"updated":63,"status":"Second Half","match_winner":{"home":"4.333","draw":"1.533","away":"4.333"},"next_goal":{"home":null,"none":null,"away":null}},"1494703":{"home_team_id":321,"away_team_id":2143,"updated":65,"status":"Second Half","match_winner":{"home":"3.5","draw":"1.444","away":"7"},"next_goal":null},"1494705":{"home_team_id":334,"away_team_id":331,"updated":55,"status":"Second Half","match_winner":{"home":"301","draw":"11","away":"1.04"},"next_goal":{"home":null,"none":null,"away":null}},"1495735":{"home_team_id":689,"away_team_id":1165,"updated":66,"status":"Second Half","match_winner":{"home":"81","draw":"21","away":"1.012"},"next_goal":{"home":null,"none":null,"away":null}},"1547995":{"home_team_id":551,"away_team_id":496,"updated":93,"status":"Second Half","match_winner":null,"next_goal":{"home":null,"none":null,"away":null}},"1547996":{"home_team_id":2177,"away_team_id":182,"updated":69,"status":"Second Half","match_winner":null,"next_goal":null},"1548147":{"home_team_id":255,"away_team_id":901,"updated":68,"status":"Second Half","match_winner":null,"next_goal":null},"1548877":{"home_team_id":1347,"away_team_id":1335,"updated":64,"status":"Second Half","match_winner":null,"next_goal":{"home":null,"none":null,"away":null}},"1560719":{"home_team_id":1363,"away_team_id":75,"updated":65,"status":"Second Half","match_winner":null,"next_goal":null},"1560727":{"home_team_id":7731,"away_team_id":73,"updated":67,"status":"Second Half","match_winner":null,"next_goal":null},"1560729":{"home_team_id":1341,"away_team_id":48,"updated":68,"status":"Second Half","match_winner":null,"next_goal":null},"1567679":{"home_team_id":2060,"away_team_id":6009,"updated":66,"status":"Second Half","match_winner":null,"next_goal":null},"1583383":{"home_team_id":1376,"away_team_id":65,"updated":67,"status":"Second Half","match_winner":null,"next_goal":null},"1548875":{"home_team_id":12844,"away_team_id":168,"updated":42,"status":"First Half","match_winner":null,"next_goal":null}}}