{"status":true,"updated_at_utc":"2026-07-04 17:30:07","server_time":1783186207,"stats":{"1567824":{"fixture_id":1567824,"home_team_id":5529,"away_team_id":31,"elapsed":29,"home":{"possession":"39%","shots_total":4,"shots_on":2,"shots_off":1,"shots_blocked":1,"shots_inside":4,"shots_outside":0,"corners":4,"fouls":7,"offsides":0,"yellow_cards":0,"red_cards":null,"saves":0,"passes_total":81,"passes_accurate":62,"passes_pct":"77%","xg":"0.42"},"away":{"possession":"61%","shots_total":0,"shots_on":0,"shots_off":0,"shots_blocked":0,"shots_inside":0,"shots_outside":0,"corners":0,"fouls":2,"offsides":1,"yellow_cards":1,"red_cards":null,"saves":2,"passes_total":141,"passes_accurate":125,"passes_pct":"89%","xg":"0.00"}}},"api_quota":{"used":null,"limit":600000}}