{"status":true,"updated_at_utc":"2026-07-18 22:48:02","server_time":1784414882,"stats":{"1591865":{"fixture_id":1591865,"home_team_id":2,"away_team_id":10,"elapsed":85,"home":{"possession":"46%","shots_total":17,"shots_on":8,"shots_off":6,"shots_blocked":3,"shots_inside":11,"shots_outside":6,"corners":2,"fouls":12,"offsides":2,"yellow_cards":null,"red_cards":null,"saves":4,"passes_total":401,"passes_accurate":366,"passes_pct":"91%","xg":"2.51"},"away":{"possession":"54%","shots_total":17,"shots_on":9,"shots_off":2,"shots_blocked":6,"shots_inside":14,"shots_outside":3,"corners":4,"fouls":8,"offsides":3,"yellow_cards":null,"red_cards":null,"saves":5,"passes_total":460,"passes_accurate":421,"passes_pct":"92%","xg":"1.79"}}},"api_quota":{"used":null,"limit":600000}}