{"status":true,"updated_at_utc":"2026-07-23 03:10:05","server_time":1784776205,"stats":{"1490342":{"fixture_id":1490342,"home_team_id":1616,"away_team_id":1606,"elapsed":30,"home":{"possession":"32%","shots_total":3,"shots_on":1,"shots_off":1,"shots_blocked":1,"shots_inside":1,"shots_outside":2,"corners":2,"fouls":2,"offsides":null,"yellow_cards":null,"red_cards":null,"saves":1,"passes_total":97,"passes_accurate":73,"passes_pct":"75%","xg":"0.22"},"away":{"possession":"68%","shots_total":6,"shots_on":1,"shots_off":3,"shots_blocked":2,"shots_inside":3,"shots_outside":3,"corners":1,"fouls":1,"offsides":null,"yellow_cards":null,"red_cards":null,"saves":0,"passes_total":216,"passes_accurate":193,"passes_pct":"89%","xg":"0.23"}},"1490343":{"fixture_id":1490343,"home_team_id":1605,"away_team_id":20787,"elapsed":30,"home":{"possession":"55%","shots_total":0,"shots_on":0,"shots_off":0,"shots_blocked":0,"shots_inside":0,"shots_outside":0,"corners":0,"fouls":3,"offsides":1,"yellow_cards":null,"red_cards":null,"saves":2,"passes_total":152,"passes_accurate":123,"passes_pct":"81%","xg":"0.00"},"away":{"possession":"45%","shots_total":2,"shots_on":2,"shots_off":0,"shots_blocked":0,"shots_inside":1,"shots_outside":1,"corners":1,"fouls":7,"offsides":1,"yellow_cards":null,"red_cards":null,"saves":0,"passes_total":121,"passes_accurate":98,"passes_pct":"81%","xg":"0.26"}},"1490344":{"fixture_id":1490344,"home_team_id":1596,"away_team_id":1598,"elapsed":30,"home":{"possession":"51%","shots_total":3,"shots_on":2,"shots_off":1,"shots_blocked":0,"shots_inside":2,"shots_outside":1,"corners":0,"fouls":5,"offsides":2,"yellow_cards":null,"red_cards":null,"saves":1,"passes_total":112,"passes_accurate":86,"passes_pct":"77%","xg":"0.18"},"away":{"possession":"49%","shots_total":7,"shots_on":2,"shots_off":4,"shots_blocked":1,"shots_inside":5,"shots_outside":2,"corners":1,"fouls":3,"offsides":1,"yellow_cards":null,"red_cards":null,"saves":2,"passes_total":103,"passes_accurate":86,"passes_pct":"83%","xg":"0.57"}},"1490345":{"fixture_id":1490345,"home_team_id":1617,"away_team_id":1597,"elapsed":30,"home":{"possession":"58%","shots_total":1,"shots_on":0,"shots_off":1,"shots_blocked":0,"shots_inside":1,"shots_outside":0,"corners":1,"fouls":1,"offsides":null,"yellow_cards":null,"red_cards":null,"saves":1,"passes_total":162,"passes_accurate":143,"passes_pct":"88%","xg":"0.03"},"away":{"possession":"42%","shots_total":3,"shots_on":1,"shots_off":1,"shots_blocked":1,"shots_inside":3,"shots_outside":0,"corners":3,"fouls":4,"offsides":null,"yellow_cards":null,"red_cards":null,"saves":0,"passes_total":117,"passes_accurate":95,"passes_pct":"81%","xg":"0.52"}},"1490337":{"fixture_id":1490337,"home_team_id":16489,"away_team_id":1595,"elapsed":69,"home":{"possession":"50%","shots_total":5,"shots_on":3,"shots_off":2,"shots_blocked":0,"shots_inside":3,"shots_outside":2,"corners":3,"fouls":4,"offsides":0,"yellow_cards":1,"red_cards":null,"saves":1,"passes_total":306,"passes_accurate":269,"passes_pct":"88%","xg":"0.61"},"away":{"possession":"50%","shots_total":5,"shots_on":2,"shots_off":2,"shots_blocked":1,"shots_inside":3,"shots_outside":2,"corners":2,"fouls":10,"offsides":1,"yellow_cards":1,"red_cards":null,"saves":2,"passes_total":318,"passes_accurate":287,"passes_pct":"90%","xg":"0.92"}},"1490341":{"fixture_id":1490341,"home_team_id":1610,"away_team_id":25484,"elapsed":46,"home":{"possession":"49%","shots_total":3,"shots_on":1,"shots_off":2,"shots_blocked":0,"shots_inside":2,"shots_outside":1,"corners":2,"fouls":9,"offsides":3,"yellow_cards":2,"red_cards":null,"saves":0,"passes_total":240,"passes_accurate":216,"passes_pct":"90%","xg":"0.17"},"away":{"possession":"51%","shots_total":0,"shots_on":0,"shots_off":0,"shots_blocked":0,"shots_inside":0,"shots_outside":0,"corners":0,"fouls":2,"offsides":0,"yellow_cards":1,"red_cards":null,"saves":1,"passes_total":257,"passes_accurate":222,"passes_pct":"86%","xg":"0.00"}}},"api_quota":{"used":null,"limit":600000}}