{"status":true,"updated_at_utc":"2026-07-12 15:50:07","server_time":1783871407,"stats":{"1494201":{"fixture_id":1494201,"home_team_id":371,"away_team_id":370,"elapsed":63,"home":{"possession":"49%","shots_total":4,"shots_on":2,"shots_off":2,"shots_blocked":0,"shots_inside":3,"shots_outside":1,"corners":2,"fouls":6,"offsides":null,"yellow_cards":null,"red_cards":null,"saves":3,"passes_total":399,"passes_accurate":357,"passes_pct":"89%","xg":null},"away":{"possession":"51%","shots_total":11,"shots_on":6,"shots_off":3,"shots_blocked":2,"shots_inside":7,"shots_outside":4,"corners":7,"fouls":11,"offsides":null,"yellow_cards":null,"red_cards":null,"saves":1,"passes_total":410,"passes_accurate":361,"passes_pct":"88%","xg":null}},"1494203":{"fixture_id":1494203,"home_team_id":2170,"away_team_id":372,"elapsed":64,"home":{"possession":"45%","shots_total":12,"shots_on":5,"shots_off":5,"shots_blocked":2,"shots_inside":7,"shots_outside":5,"corners":3,"fouls":4,"offsides":0,"yellow_cards":1,"red_cards":null,"saves":3,"passes_total":315,"passes_accurate":262,"passes_pct":"83%","xg":null},"away":{"possession":"55%","shots_total":12,"shots_on":3,"shots_off":4,"shots_blocked":5,"shots_inside":10,"shots_outside":2,"corners":3,"fouls":4,"offsides":1,"yellow_cards":0,"red_cards":null,"saves":3,"passes_total":387,"passes_accurate":334,"passes_pct":"86%","xg":null}},"1494693":{"fixture_id":1494693,"home_team_id":319,"away_team_id":334,"elapsed":45,"home":{"possession":"66%","shots_total":3,"shots_on":0,"shots_off":3,"shots_blocked":0,"shots_inside":3,"shots_outside":0,"corners":1,"fouls":4,"offsides":null,"yellow_cards":null,"red_cards":null,"saves":null,"passes_total":328,"passes_accurate":279,"passes_pct":"85%","xg":"0.31"},"away":{"possession":"34%","shots_total":6,"shots_on":0,"shots_off":4,"shots_blocked":2,"shots_inside":4,"shots_outside":2,"corners":1,"fouls":7,"offsides":null,"yellow_cards":null,"red_cards":null,"saves":null,"passes_total":169,"passes_accurate":118,"passes_pct":"70%","xg":"0.34"}},"1494696":{"fixture_id":1494696,"home_team_id":331,"away_team_id":320,"elapsed":45,"home":{"possession":"74%","shots_total":8,"shots_on":5,"shots_off":3,"shots_blocked":0,"shots_inside":5,"shots_outside":3,"corners":2,"fouls":5,"offsides":0,"yellow_cards":null,"red_cards":null,"saves":0,"passes_total":314,"passes_accurate":277,"passes_pct":"88%","xg":"0.81"},"away":{"possession":"26%","shots_total":1,"shots_on":0,"shots_off":0,"shots_blocked":1,"shots_inside":1,"shots_outside":0,"corners":2,"fouls":9,"offsides":1,"yellow_cards":null,"red_cards":null,"saves":4,"passes_total":107,"passes_accurate":69,"passes_pct":"64%","xg":"0.03"}},"1494697":{"fixture_id":1494697,"home_team_id":332,"away_team_id":2159,"elapsed":45,"home":{"possession":"60%","shots_total":6,"shots_on":2,"shots_off":2,"shots_blocked":2,"shots_inside":4,"shots_outside":2,"corners":2,"fouls":8,"offsides":null,"yellow_cards":1,"red_cards":null,"saves":0,"passes_total":283,"passes_accurate":251,"passes_pct":"89%","xg":"0.46"},"away":{"possession":"40%","shots_total":2,"shots_on":0,"shots_off":1,"shots_blocked":1,"shots_inside":2,"shots_outside":0,"corners":1,"fouls":6,"offsides":null,"yellow_cards":1,"red_cards":null,"saves":1,"passes_total":188,"passes_accurate":152,"passes_pct":"81%","xg":"0.11"}}},"api_quota":{"used":null,"limit":600000}}