{"status":true,"updated_at_utc":"2026-07-18 17:56:06","server_time":1784397366,"stats":{"1494704":{"fixture_id":1494704,"home_team_id":329,"away_team_id":319,"elapsed":90,"home":{"possession":"47%","shots_total":13,"shots_on":2,"shots_off":9,"shots_blocked":2,"shots_inside":11,"shots_outside":2,"corners":6,"fouls":11,"offsides":0,"yellow_cards":4,"red_cards":null,"saves":0,"passes_total":473,"passes_accurate":399,"passes_pct":"84%","xg":"0.88"},"away":{"possession":"53%","shots_total":8,"shots_on":2,"shots_off":3,"shots_blocked":3,"shots_inside":7,"shots_outside":1,"corners":4,"fouls":14,"offsides":3,"yellow_cards":1,"red_cards":null,"saves":1,"passes_total":545,"passes_accurate":460,"passes_pct":"84%","xg":"0.53"}}},"api_quota":{"used":null,"limit":600000}}