{"status":true,"updated_at_utc":"2026-07-23 15:40:05","server_time":1784821205,"stats":{"1591943":{"fixture_id":1591943,"home_team_id":661,"away_team_id":601,"elapsed":40,"home":{"possession":"43%","shots_total":4,"shots_on":1,"shots_off":2,"shots_blocked":1,"shots_inside":3,"shots_outside":1,"corners":1,"fouls":6,"offsides":1,"yellow_cards":1,"red_cards":null,"saves":0,"passes_total":136,"passes_accurate":106,"passes_pct":"78%","xg":null},"away":{"possession":"57%","shots_total":2,"shots_on":1,"shots_off":1,"shots_blocked":0,"shots_inside":2,"shots_outside":0,"corners":2,"fouls":6,"offsides":0,"yellow_cards":1,"red_cards":null,"saves":1,"passes_total":182,"passes_accurate":136,"passes_pct":"75%","xg":null}}},"api_quota":{"used":null,"limit":600000}}